[
    
    {},
    {},
    
    {
        "get_drunk": [[],[
            {
                "speaker":"Moon",
                "pivot":[0,0],
                "content": "[shake]What is this?",
                "behavior":{"speed":0.8,},
            }
        ],
            [
        {
            "speaker":"Moon",
            "pivot":[0,0],
            "content": "[wave]It makes me feel.. sleepy...",
            "behavior":{"speed":0.5},
        },],
        [{
            "speaker":"Moon",
            "pivot":[0,0],
            "content": "[wave]zzZZ",
            "behavior":{"get_sleep":true},
        }],
    ],
    },
    {
        "get_drunk": [[],[],
            [{
            "speaker":"Moon",
            "pivot":[0,0],
            "content": "I'm excited!! I'm the [shake rate=50 level=10]FLASH!",
            "behavior":{"speed":1.5},
        },
        {
            "speaker":"Moon",
            "pivot":[0,0],
            "content": "[shake rate=30 level=10]More meteors coming!!",
            "behavior":{"ammo_speed":2},
        },],
        [{
            "speaker":"Moon",
            "pivot":[0,0],
            "content": "I'm [fade]exhausted....",
            "behavior":{"speed":0.5,"ammo_speed":1},
        },
        {
            "speaker":"Moon",
            "pivot":[0,0],
            "content": "[rainbow]WHeRe aM i? HeLLo LiTTLe aNTS i LoVe You~~",
            "behavior":{"move_drunk":0.5,"speed":0.6,"ammo_speed":1},
        },
        {
            "speaker":"Moon",
            "pivot":[0,0],
            "content": "I'll destroy all of you! [shake rate=30 level=10]Sun![/shake] Don't run, fight with me!!",
            "behavior":{"shoot_randomly":0.5,"speed":1,"ammo_speed":1},
        },],
    ],
    },
]